[
  {
    "id": "contract",
    "title": "Договор (пример)",
    "description": "Шаблон договора и ключевые условия сотрудничества",
    "file": "/documents/contract-template_v1.2_2025-12-19.pdf",
    "version": "1.2",
    "effective_from": "2025-12-19",
    "summary_bullets": [
      "Предмет договора и границы работ",
      "Порядок приёмки результатов",
      "Ответственность сторон",
      "Конфиденциальность",
      "Порядок оплаты и закрывающие документы"
    ],
    "disclaimer": "Публикуется в ознакомительных целях. Финальные условия фиксируются в подписанной версии документов.",
    "public": true
  },
  {
    "id": "sla",
    "title": "SLA / Поддержка",
    "description": "Условия технической поддержки и обслуживания после внедрения",
    "file": "/documents/sla_v1.0_2025-12-19.pdf",
    "version": "1.0",
    "effective_from": "2025-12-19",
    "summary_bullets": [
      "Время реакции на инциденты",
      "Окна технической поддержки",
      "Процедуры эскалации",
      "Гарантии доступности системы",
      "Процедуры обновлений и патчей"
    ],
    "disclaimer": "Условия поддержки могут варьироваться в зависимости от тарифа и специфики проекта.",
    "public": true
  },
  {
    "id": "privacy",
    "title": "Политика конфиденциальности",
    "description": "Как мы обрабатываем персональные данные",
    "file": "/documents/privacy_v1.0_2025-12-19.pdf",
    "version": "1.0",
    "effective_from": "2025-12-19",
    "summary_bullets": [
      "Какие данные собираем",
      "Цели обработки данных",
      "Права пользователей",
      "Меры защиты информации",
      "Передача данных третьим лицам"
    ],
    "disclaimer": "Политика соответствует требованиям 152-ФЗ о персональных данных.",
    "public": true
  },
  {
    "id": "implementation",
    "title": "Регламент внедрения",
    "description": "Порядок работ и этапы внедрения AI-решений",
    "file": "/documents/implementation-regulation_v1.1_2025-12-19.pdf",
    "version": "1.1",
    "effective_from": "2025-12-19",
    "summary_bullets": [
      "Этапы проекта и их длительность",
      "Критерии приёмки каждого этапа",
      "Процедуры согласования и демонстраций",
      "Журналирование изменений",
      "Процедуры тестирования и запуска"
    ],
    "disclaimer": "Регламент может быть адаптирован под специфику конкретного проекта.",
    "public": true
  },
  {
    "id": "nda",
    "title": "NDA (пример)",
    "description": "Шаблон соглашения о неразглашении конфиденциальной информации",
    "file": "/documents/nda-template_v1.0_2025-12-19.pdf",
    "version": "1.0",
    "effective_from": "2025-12-19",
    "summary_bullets": [
      "Определение конфиденциальной информации",
      "Обязательства сторон",
      "Срок действия соглашения",
      "Исключения из режима конфиденциальности",
      "Ответственность за нарушение"
    ],
    "disclaimer": "Шаблон для ознакомления. Финальная версия согласовывается сторонами.",
    "public": true
  },
  {
    "id": "roi-method",
    "title": "Методика оценки эффекта",
    "description": "Подход к измерению ROI и KPI от внедрения AI-решений",
    "file": "/documents/roi-method_v1.0_2025-12-19.pdf",
    "version": "1.0",
    "effective_from": "2025-12-19",
    "summary_bullets": [
      "Метрики для оценки эффективности",
      "Подход к измерению до и после",
      "Факторы, влияющие на результат",
      "Периодичность замеров",
      "Интерпретация результатов"
    ],
    "disclaimer": "Методика описывает подход к измерениям и не гарантирует достижение конкретных цифр. Показатели зависят от исходных данных и процессов заказчика.",
    "public": true
  }
]

